{
	"firstname": "Diedre",
	"date_employment": "2014-05-15T00:00:00.000Z",
	"total_value": 1100,
	"id": "7b8411e0-400e-4c8a-9b9f-861fcacaa58b",
	"rewards": [
		{
			"description": "Je je eigen inzet/klus regelt",
			"id": "7b8411e0-4cf5-4247-a60a-317cab87e54d",
			"date": "2024-05-15 11:10:04",
			"value": 50
		},
		{
			"description": "Nieuwe lead",
			"id": "7b8411e0-a6c5-4701-9b31-122c3f5ce3de",
			"date": "2024-05-15 11:10:04",
			"value": 50
		},
		{
			"description": "Gestarte kandidaat (externe) vinden op aanvraag",
			"id": "7b8411e0-fe14-4217-89d8-7d0754da0da0",
			"date": "2024-05-15 11:10:04",
			"value": 100
		},
		{
			"description": "Nieuwe lead",
			"id": "7b8411e0-6f27-406e-b1e8-149e24fc78e8",
			"date": "2024-05-15 11:10:04",
			"value": 50
		},
		{
			"description": "Nieuwe lead",
			"id": "7b8411e0-edbb-4a8e-86ad-3b3ae8a3713e",
			"date": "2024-05-15 11:10:04",
			"value": 50
		},
		{
			"description": "Lead die tot een inzet/deal leidt",
			"id": "7b8411e0-1dd1-4e2b-b82f-d4f60efc5f60",
			"date": "2024-05-15 11:10:04",
			"value": 100
		},
		{
			"description": "Nieuwe kandidaat die we aanbieding doen",
			"id": "7b8411e0-258f-4fa1-9851-2786ab1da449",
			"date": "2024-05-15 11:10:04",
			"value": 200
		},
		{
			"description": "Nieuwe kandidaat die we aanbieding doen",
			"id": "7b8411e0-6f2b-455f-b9ba-33e79c9d8b61",
			"date": "2024-05-15 11:10:04",
			"value": 200
		},
		{
			"description": "Lead die tot een inzet/deal leidt",
			"id": "7b8411e0-e54e-4e43-9df7-4b4f32640db2",
			"date": "2024-05-15 11:10:04",
			"value": 100
		},
		{
			"description": "Nieuwe kandidaat die we aanbieding doen",
			"id": "7b8411e0-e23a-4a7b-bae5-545c50c23693",
			"date": "2024-05-15 11:10:04",
			"value": 200
		}
	],
	"lastname": "De Wit",
	"_id": "0074",
	"updatedTimestamp": "2024-05-15T11:10:04.000Z",
	"creationTimestamp": "2024-05-15T11:10:04.000Z"
}