{
	"firstname": "Shaina",
	"date_employment": "2014-05-13T00:00:00.000Z",
	"total_value": 1500,
	"id": "73886630-4730-4488-97f6-59a07f32e4d3",
	"rewards": [
		{
			"description": "Nieuwe kandidaat door proeftijd heen",
			"uuid": "73886630-673c-4646-b566-b40d352a1568",
			"date": "2024-05-13 21:57:50",
			"value": 1000
		},
		{
			"description": "Nieuwe lead",
			"uuid": "73886630-36e2-4152-bfe2-ba4bfbb06d76",
			"date": "2024-05-13 21:57:50",
			"value": 50
		},
		{
			"description": "Nieuwe lead",
			"uuid": "73886630-c020-47bc-875d-a5587a0deaee",
			"date": "2024-05-13 21:57:50",
			"value": 50
		},
		{
			"description": "Nieuwe kandidaat die we aanbieding doen",
			"uuid": "73886630-08ca-43cf-9708-7086ab6f121f",
			"date": "2024-05-13 21:57:50",
			"value": 200
		},
		{
			"description": "Nieuwe kandidaat die we aanbieding doen",
			"uuid": "73886630-ce4f-489a-ab82-72fccac2f60f",
			"date": "2024-05-13 21:57:50",
			"value": 200
		}
	],
	"lastname": "Van den Berg",
	"updatedTimestamp": "2024-05-13T21:57:50.000Z",
	"creationTimestamp": "2024-05-13T21:57:50.000Z"
}